elm_magic/__init__.py
elm_magic/cli.py
elm_magic/elm_magic.py
elm_magic-0.1.0.dist-info/DESCRIPTION.rst
elm_magic-0.1.0.dist-info/METADATA
elm_magic-0.1.0.dist-info/RECORD
elm_magic-0.1.0.dist-info/WHEEL
elm_magic-0.1.0.dist-info/entry_points.txt
elm_magic-0.1.0.dist-info/metadata.json
elm_magic-0.1.0.dist-info/top_level.txt
