Metadata-Version: 2.0
Name: elm-magic
Version: 0.1.0
Summary: Elm Magic provides IPython magic commands that execute elm-lang code
Home-page: https://github.com/ali--/elm_magic
Author: Ali Rathore
Author-email: ali1rathore@gmail.com
License: GNU General Public License v3
Keywords: elm_magic
Platform: UNKNOWN
Classifier: Development Status :: 2 - Pre-Alpha
Classifier: Intended Audience :: Developers
Classifier: License :: OSI Approved :: GNU General Public License v3 (GPLv3)
Classifier: Natural Language :: English
Classifier: Programming Language :: Python :: 2
Classifier: Programming Language :: Python :: 2.6
Classifier: Programming Language :: Python :: 2.7
Classifier: Programming Language :: Python :: 3
Classifier: Programming Language :: Python :: 3.3
Classifier: Programming Language :: Python :: 3.4
Classifier: Programming Language :: Python :: 3.5
Requires-Dist: Click (>=6.0)
Requires-Dist: ipython (>=1.0)
